singer_sdk/__init__.py
singer_sdk/_logging.py
singer_sdk/about.py
singer_sdk/authenticators.py
singer_sdk/batch.py
singer_sdk/exceptions.py
singer_sdk/io_base.py
singer_sdk/logging.py
singer_sdk/mapper.py
singer_sdk/mapper_base.py
singer_sdk/metrics.py
singer_sdk/pagination.py
singer_sdk/plugin_base.py
singer_sdk/py.typed
singer_sdk/tap_base.py
singer_sdk/target_base.py
singer_sdk/typing.py
singer_sdk/cli/__init__.py
singer_sdk/configuration/__init__.py
singer_sdk/configuration/_dict_config.py
singer_sdk/connectors/__init__.py
singer_sdk/connectors/sql.py
singer_sdk/contrib/__init__.py
singer_sdk/contrib/batch_encoder_jsonl.py
singer_sdk/contrib/batch_encoder_parquet.py
singer_sdk/contrib/msgspec.py
singer_sdk/contrib/filesystem/__init__.py
singer_sdk/contrib/filesystem/config.py
singer_sdk/contrib/filesystem/stream.py
singer_sdk/contrib/filesystem/tap.py
singer_sdk/helpers/__init__.py
singer_sdk/helpers/_batch.py
singer_sdk/helpers/_catalog.py
singer_sdk/helpers/_classproperty.py
singer_sdk/helpers/_compat.py
singer_sdk/helpers/_conformers.py
singer_sdk/helpers/_flattening.py
singer_sdk/helpers/_state.py
singer_sdk/helpers/_typing.py
singer_sdk/helpers/_util.py
singer_sdk/helpers/capabilities.py
singer_sdk/helpers/jsonpath.py
singer_sdk/helpers/types.py
singer_sdk/internal/__init__.py
singer_sdk/schema/__init__.py
singer_sdk/schema/source.py
singer_sdk/schemas/logs.schema.json
singer_sdk/singerlib/__init__.py
singer_sdk/singerlib/catalog.py
singer_sdk/singerlib/exceptions.py
singer_sdk/singerlib/json.py
singer_sdk/singerlib/messages.py
singer_sdk/singerlib/schema.py
singer_sdk/singerlib/utils.py
singer_sdk/singerlib/encoding/__init__.py
singer_sdk/singerlib/encoding/base.py
singer_sdk/singerlib/encoding/simple.py
singer_sdk/sinks/__init__.py
singer_sdk/sinks/batch.py
singer_sdk/sinks/core.py
singer_sdk/sinks/record.py
singer_sdk/sinks/sql.py
singer_sdk/sql/__init__.py
singer_sdk/sql/connector.py
singer_sdk/sql/sink.py
singer_sdk/sql/stream.py
singer_sdk/sql/tap.py
singer_sdk-0.53.5.dist-info/METADATA
singer_sdk-0.53.5.dist-info/WHEEL
singer_sdk-0.53.5.dist-info/entry_points.txt
singer_sdk-0.53.5.dist-info/licenses/LICENSE
singer_sdk-0.53.5.dist-info/RECORD
