Metadata-Version: 2.4
Name: singer-sdk
Version: 0.53.5
Summary: A framework for building Singer taps and targets
Project-URL: Homepage, https://sdk.meltano.com/en/latest/
Project-URL: Repository, https://github.com/meltano/sdk
Project-URL: Documentation, https://sdk.meltano.com/en/latest/
Project-URL: Issue Tracker, https://github.com/meltano/sdk/issues
Project-URL: Twitter, https://twitter.com/meltanodata/
Project-URL: Changelog, https://github.com/meltano/sdk/blob/main/CHANGELOG.md
Project-URL: Slack, https://meltano.com/slack
Project-URL: Youtube, https://www.youtube.com/meltano
Author-email: Meltano Team and Contributors <hello@meltano.com>
Maintainer-email: Meltano Team and Contributors <hello@meltano.com>
License-Expression: Apache-2.0
License-File: LICENSE
Keywords: ELT,Meltano,Meltano SDK,Singer,Singer SDK
Classifier: Intended Audience :: Developers
Classifier: Operating System :: OS Independent
Classifier: Programming Language :: Python :: 3.10
Classifier: Programming Language :: Python :: 3.11
Classifier: Programming Language :: Python :: 3.12
Classifier: Programming Language :: Python :: 3.13
Classifier: Programming Language :: Python :: 3.14
Classifier: Programming Language :: Python :: Implementation :: CPython
Classifier: Topic :: Software Development :: Libraries :: Application Frameworks
Classifier: Typing :: Typed
Requires-Python: >=3.10
Requires-Dist: backports-datetime-fromisoformat>=2.0.1; python_version < '3.11'
Requires-Dist: click<9,>=8.2
Requires-Dist: fsspec>=2024.9.0
Requires-Dist: importlib-metadata>=6.5; python_version < '3.12'
Requires-Dist: inflection>=0.5.1
Requires-Dist: joblib>=1.3.0
Requires-Dist: jsonpath-ng>=1.5.3
Requires-Dist: jsonschema>=4.16.0
Requires-Dist: packaging>=23.1
Requires-Dist: python-backoff>=2.2.2
Requires-Dist: python-dotenv>=0.20
Requires-Dist: pyyaml>=6.0
Requires-Dist: referencing>=0.30.0
Requires-Dist: requests>=2.25.1
Requires-Dist: simpleeval!=1.0.1,>=0.9.13
Requires-Dist: simplejson>=3.17.6
Requires-Dist: sqlalchemy>=2
Requires-Dist: typing-extensions>=4.5.0; python_version < '3.13'
Requires-Dist: universal-pathlib>=0.2.6
Provides-Extra: faker
Requires-Dist: faker>=22.5; extra == 'faker'
Provides-Extra: jwt
Requires-Dist: cryptography>=3.4.6; extra == 'jwt'
Requires-Dist: pyjwt>=2.4.0; extra == 'jwt'
Provides-Extra: msgspec
Requires-Dist: msgspec>=0.19.0; extra == 'msgspec'
Provides-Extra: parquet
Requires-Dist: pyarrow>=15; extra == 'parquet'
Provides-Extra: s3
Requires-Dist: s3fs>=2024.9.0; extra == 's3'
Provides-Extra: sql
Requires-Dist: sqlalchemy>=2; extra == 'sql'
Provides-Extra: ssh
Requires-Dist: paramiko>=3.3.0; extra == 'ssh'
Provides-Extra: testing
Requires-Dist: pytest>=9; extra == 'testing'
